qalita/__init__.py
qalita/__main__.py
qalita/_frontend/package.json
qalita/_frontend/server.js
qalita/_frontend/.next/static/BNkGe67QNZQE3gQg47i0I/_buildManifest.js
qalita/_frontend/.next/static/BNkGe67QNZQE3gQg47i0I/_clientMiddlewareManifest.json
qalita/_frontend/.next/static/BNkGe67QNZQE3gQg47i0I/_ssgManifest.js
qalita/_frontend/.next/static/chunks/0f84739db4a8acc7.js
qalita/_frontend/.next/static/chunks/1107bdca1eff6d34.css
qalita/_frontend/.next/static/chunks/236f7e5abd6f09ff.js
qalita/_frontend/.next/static/chunks/30ea11065999f7ac.js
qalita/_frontend/.next/static/chunks/4b0c5de8d4cc313f.js
qalita/_frontend/.next/static/chunks/4dd28bc3f722184a.js
qalita/_frontend/.next/static/chunks/6c99da4248e4fcfc.js
qalita/_frontend/.next/static/chunks/711d597b816a80c1.js
qalita/_frontend/.next/static/chunks/7340adf74ff47ec0.js
qalita/_frontend/.next/static/chunks/a6dad97d9634a72d.js
qalita/_frontend/.next/static/chunks/a6dad97d9634a72d.js.map
qalita/_frontend/.next/static/chunks/bb29c2be4df20a40.js
qalita/_frontend/.next/static/chunks/ecf559101be0ae12.js
qalita/_frontend/.next/static/chunks/ff1a16fafef87110.js
qalita/_frontend/.next/static/chunks/turbopack-25186fc8e1264445.js
qalita/_frontend/node_modules/@img/colour/color.cjs
qalita/_frontend/node_modules/@img/colour/index.cjs
qalita/_frontend/node_modules/@img/colour/package.json
qalita/_frontend/node_modules/@img/sharp-libvips-linux-x64/README.md
qalita/_frontend/node_modules/@img/sharp-libvips-linux-x64/package.json
qalita/_frontend/node_modules/@img/sharp-libvips-linux-x64/versions.json
qalita/_frontend/node_modules/@img/sharp-libvips-linux-x64/lib/index.js
qalita/_frontend/node_modules/@img/sharp-libvips-linux-x64/lib/libvips-cpp.so.8.17.3
qalita/_frontend/node_modules/@img/sharp-libvips-linux-x64/lib/glib-2.0/include/glibconfig.h
qalita/_frontend/node_modules/@img/sharp-libvips-linuxmusl-x64/README.md
qalita/_frontend/node_modules/@img/sharp-libvips-linuxmusl-x64/package.json
qalita/_frontend/node_modules/next/dist/compiled/ci-info/index.js
qalita/_frontend/node_modules/next/dist/compiled/ci-info/package.json
qalita-2.6.2.dist-info/METADATA
qalita-2.6.2.dist-info/WHEEL
qalita-2.6.2.dist-info/entry_points.txt
qalita-2.6.2.dist-info/licenses/LICENSE
qalita-2.6.2.dist-info/RECORD
